{
  "categories": [
    {
      "id": "groceries",
      "name": "Alimente & BДѓuturi",
      "emoji": "рџ›’",
      "keywords": [
        "albert heijn", "jumbo", "lidl", "aldi", "plus supermarkt", "dirk", "coop",
        "hoogvliet", "spar", "vomar", "picnic", "dekamarkt", "jan linders",
        "kaufland", "mega image", "carrefour", "auchan", "penny", "profi",
        "supermarkt", "supermarket", "boodschappen", "vers", "bakker", "slager",
        "markt", "versmarkt", "poelier", "vishandel", "groente"
      ]
    },
    {
      "id": "restaurants",
      "name": "Restaurante & Cafenele",
      "emoji": "рџЌЅпёЏ",
      "keywords": [
        "restaurant", "cafe", "cafetaria", "eetcafe", "broodjeszaak", "lunchroom",
        "mcdonald", "kfc", "burger king", "subway", "dominos", "new york pizza",
        "thuisbezorgd", "deliveroo", "uber eats", "just eat",
        "starbucks", "costa coffee", "bagels beans", "la place", "bagel",
        "pizzerie", "cafenea", "fast food", "snackbar", "frituur", "shoarma",
        "sushi", "thai", "chinees", "indiaas", "grieks", "italiaans"
      ]
    },
    {
      "id": "transport",
      "name": "Transport",
      "emoji": "рџљ—",
      "keywords": [
        "ns ", "ovchipkaart", "ov-chipkaart", "9292", "connexxion", "arriva", "ret", "gvb", "htm", "qbuzz",
        "shell", "bp", "esso", "tinq", "tango", "neom", "tamoil", "total",
        "bolt", "uber", "greenwheels", "sixt", "enterprise", "hertz",
        "parkeergarage", "parkeren", "parkmobile", "yellowbrick", "q-park",
        "rdw", "apk", "autogarage", "bandenservice", "kwikfit",
        "petrom", "omv", "mol", "rompetrol",
        "benzine", "diesel", "tankstation", "brandstof"
      ]
    },
    {
      "id": "utilities",
      "name": "UtilitДѓИ›i",
      "emoji": "рџ’Ў",
      "keywords": [
        "vattenfall", "eneco", "essent", "nuon", "greenchoice", "budget energie", "oxxio",
        "ziggo", "kpn", "t-mobile", "vodafone", "tele2", "simpel", "ben ", "hollandsnieuwe",
        "vitens", "dunea", "waternet", "evides", "brabant water",
        "enel", "engie", "digi", "orange", "telekom",
        "energie", "stroom", "gas ", "water ", "internet", "glasvezel"
      ]
    },
    {
      "id": "health",
      "name": "SДѓnДѓtate",
      "emoji": "рџ’Љ",
      "keywords": [
        "apotheek", "pharmacie", "farmacie",
        "etos", "kruidvat", "da drogist", "boots", "trekpleister",
        "huisarts", "dokter", "ziekenhuis", "tandarts", "fysiotherapie",
        "optician", "specsavers", "pearle", "brillen",
        "gym", "sportschool", "fitness", "basic fit", "onefit",
        "catena", "sensiblu", "helpnet", "medic", "spital",
        "drogist", "gezondheid", "kapper", "schoonheid", "beauty"
      ]
    },
    {
      "id": "clothing",
      "name": "ГЋmbrДѓcДѓminte",
      "emoji": "рџ‘•",
      "keywords": [
        "h&m", "zara", "uniqlo", "primark", "c&a", "mango", "cos ",
        "only", "jack jones", "scotch soda", "the sting", "gsus", "g-star",
        "nike", "adidas", "puma", "asics", "new balance",
        "decathlon", "intersport",
        "wehkamp", "zalando", "about you",
        "reserved", "new yorker", "peek cloppenburg",
        "schoenen", "kleding", "mode", "fashion"
      ]
    },
    {
      "id": "home",
      "name": "CasДѓ & ГЋntreИ›inere",
      "emoji": "рџЏ ",
      "keywords": [
        "ikea", "praxis", "gamma", "karwei", "hornbach", "intratuin", "formido",
        "kwantum", "jysk", "xenos", "action", "blokker", "hema", "casa",
        "coolblue", "mediamarkt", "expert", "bol.com", "amazon", "wehkamp elektronica",
        "apple", "samsung", "dyson",
        "schoonmaak", "cleaning", "woningbouw", "onderhoud",
        "loodgieter", "elektricien", "schilder", "aannemer",
        "dedeman", "leroy merlin", "bricolage",
        "wonen", "tuin", "meubel", "lamp", "gereedschap"
      ]
    },
    {
      "id": "entertainment",
      "name": "Divertisment & VacanИ›Дѓ",
      "emoji": "рџЋ¬",
      "keywords": [
        "netflix", "spotify", "videoland", "disney", "hbo", "amazon prime", "apple tv",
        "patreon", "twitch", "youtube premium", "adobe", "canva",
        "pathe", "vue cinema", "kinepolis", "cinema", "bioscoop",
        "ticketmaster", "eventbrite", "concert", "theater", "museum",
        "booking.com", "airbnb", "hotels.com", "expedia", "trivago",
        "ryanair", "klm", "transavia", "easyjet", "wizz",
        "vakantie", "reizen", "hotel", "vlucht", "bilet avion",
        "steam", "playstation", "nintendo", "xbox", "games"
      ]
    },
    {
      "id": "children",
      "name": "Copii",
      "emoji": "рџ‘ЁвЂЌрџ‘©вЂЌрџ‘§вЂЌрџ‘¦",
      "keywords": [
        "school", "scoala", "schoolboeken", "schoolspullen",
        "speelgoed", "toys", "intertoys", "smyths",
        "kinderopvang", "bso", "naschoolse",
        "sportclub", "voetbal", "zwemles", "muziekles", "dansles",
        "kinderfietsen", "kinderkleding", "baby"
      ]
    },
    {
      "id": "personal",
      "name": "Bani Personali",
      "emoji": "рџ’°",
      "keywords": [
        "bol.com boeken", "bruna", "selexyz", "donner", "readshop", "libris",
        "kapper", "barbier", "nagels", "spa ", "wellness",
        "cadeau", "gift", "present", "card", "bon cadeau",
        "donatie", "goededoelen", "aidsfonds", "amnesty",
        "lunch", "koffie werk"
      ]
    },
    {
      "id": "investments",
      "name": "InvestiИ›ii & Economii",
      "emoji": "рџ“€",
      "keywords": [
        "degiro", "nse", "vanguard", "etf", "beurs",
        "brand new day", "meesman", "northern trust",
        "spaarrekening", "sparen", "deposito",
        "investitie", "economii"
      ]
    },
    {
      "id": "other",
      "name": "Altele",
      "emoji": "рџ“¦",
      "keywords": []
    }
  ]
}
